{
  "bron_1990_2000": "CBS 70188ned — Gemiddeld persoonlijk inkomen, alle personen (x1000 EUR)",
  "bron_2000_2014": "CBS 70957ned — Gemiddeld persoonlijk inkomen, personen met inkomen (x1000 EUR)",
  "bron_2011_2024": "CBS 83931NED — Persoonlijk inkomen, mean/median (x1000 EUR)",
  "noot": "Tabellen zijn niet direct vergelijkbaar: 70188ned = alle personen, 70957ned = personen met inkomen, 83931NED = per inkomensconcept",

  "alle_personen_1990_2000": {
    "velden": ["jaar", "primair_inkomen", "bruto_inkomen", "persoonlijk_inkomen", "besteedbaar_inkomen", "gestandaardiseerd_inkomen"],
    "data": [
      [1990, 9.4, 12.5, 11.1, 7.7, 12.8],
      [1991, 9.8, 13.1, 11.7, 8.0, 13.3],
      [1992, 10.3, 13.8, 12.3, 8.3, 13.7],
      [1993, 10.3, 13.9, 12.4, 8.4, 13.9],
      [1994, 10.3, 14.0, 12.7, 8.7, 14.3],
      [1995, 10.7, 14.3, 13.0, 9.0, 14.8],
      [1996, 10.9, 14.6, 13.3, 9.3, 15.2],
      [1997, 11.3, 15.0, 13.8, 9.6, 15.7],
      [1998, 11.8, 15.5, 14.1, 10.0, 16.2],
      [1999, 12.6, 16.3, 14.9, 10.4, 16.9],
      [2000, 13.2, 17.2, 15.7, 11.0, 17.8]
    ]
  },

  "personen_met_inkomen_2000_2014": {
    "velden": ["jaar", "personen_x1000", "gem_persoonlijk_inkomen", "gem_gestandaardiseerd_inkomen"],
    "data": [
      [2000, 11622, 21.0, 18.7],
      [2001, 11734, 22.4, 20.4],
      [2002, 11835, 23.2, 21.0],
      [2003, 11852, 23.7, 21.0],
      [2004, 11897, 24.3, 21.5],
      [2005, 11993, 24.7, 21.8],
      [2006, 12090, 25.8, 22.7],
      [2007, 12246, 26.8, 24.3],
      [2008, 12411, 27.9, 24.7],
      [2009, 12489, 28.3, 24.9],
      [2010, 12596, 28.4, 24.8],
      [2011, 12712, 28.9, 25.0],
      [2012, 12782, 29.0, 25.0],
      [2013, 12815, 29.4, 25.2],
      [2014, 12925, 29.9, 26.3]
    ]
  },

  "primair_inkomen_2011_2024": {
    "velden": ["jaar", "personen_x1000", "gemiddelde", "mediaan"],
    "data": [
      [2011, 9168, 36.5, 30.5],
      [2012, 9153, 37.0, 30.5],
      [2013, 9075, 37.5, 30.9],
      [2014, 9077, 38.2, 31.4],
      [2015, 9142, 38.2, 31.6],
      [2016, 9241, 38.9, 32.3],
      [2017, 9413, 39.8, 33.2],
      [2018, 9609, 40.8, 34.2],
      [2019, 9781, 42.3, 35.6],
      [2020, 9783, 43.8, 37.2],
      [2021, 9933, 45.3, 38.3],
      [2022, 10159, 48.0, 41.0],
      [2023, 10345, 50.8, 43.5],
      [2024, 10421, 53.8, 46.4]
    ]
  }
}
